{"people also ask": {"change_type": "unchanged"}, "videos": {"change_type": "unchanged"}, "related searches": {"change_type": "unchanged"}, "knowledge panel": {"change_type": "unchanged"}, "see results about": {"change_type": "unchanged"}, "organic": {"https://www.ohrc.on.ca": {"change": 0, "title": "3. Gender identity and gender expression - Ontario Human ...", "pos1": 1, "pos2": 1, "change_type": "unchanged"}, "https://en.wikipedia.org": {"change": 0, "title": "Gender expression - Wikipedia", "pos1": 2, "pos2": 2, "change_type": "unchanged"}, "https://myhealth.alberta.ca": {"change": 0, "title": "Gender, gender identity, and gender expression - MyHealth ...", "pos1": 3, "pos2": 3, "change_type": "unchanged"}, "https://www.hrc.org": {"change": -1, "title": "Sexual Orientation and Gender Identity Definitions - Human ...", "pos1": 4, "pos2": 5, "change_type": "move"}, "https://www.npr.org": {"change": 1, "title": "A Guide to Understanding Gender Identity and Pronouns - NPR", "pos1": 5, "pos2": 4, "change_type": "move"}, "https://www.geneseo.edu": {"change": 0, "title": "Understanding Gender Identity and Gender Expression", "pos1": 6, "pos2": 6, "change_type": "unchanged"}, "https://www.verywellmind.com": {"change": 0, "title": "What Is Gender Expression? - Verywell Mind", "pos1": 7, "pos2": 7, "change_type": "unchanged"}, "https://www.talkspace.com": {"change": 0, "title": "Gender Identity vs. Gender Expression: What's the Difference?", "pos1": 8, "pos2": 8, "change_type": "unchanged"}, "https://genderspectrum.org": {"change": 0, "title": "Understanding Gender", "pos1": 9, "pos2": 9, "change_type": "unchanged"}}}